Stoichiograph-0.1.2.dist-info/DESCRIPTION.rst
Stoichiograph-0.1.2.dist-info/METADATA
Stoichiograph-0.1.2.dist-info/RECORD
Stoichiograph-0.1.2.dist-info/WHEEL
Stoichiograph-0.1.2.dist-info/entry_points.txt
Stoichiograph-0.1.2.dist-info/metadata.json
Stoichiograph-0.1.2.dist-info/top_level.txt
stoichiograph/__init__.py
stoichiograph/__main__.py
stoichiograph/speller.py
stoichiograph/stoichiograph.py
