Metadata-Version: 2.0
Name: Stoichiograph
Version: 0.1.2
Summary: Spell words with elemental symbols from the periodic table ("He", "Cu", etc).
Home-page: https://github.com/mesbahamin/stoichiograph
Author: Amin Mesbah
Author-email: mesbahamin@gmail.com
License: MIT
Keywords: command-line chemistry words fun combinatorics spelling
Platform: UNKNOWN
Classifier: Development Status :: 4 - Beta
Classifier: Environment :: Console
Classifier: Intended Audience :: Education
Classifier: Intended Audience :: Developers
Classifier: Intended Audience :: End Users/Desktop
Classifier: Topic :: Scientific/Engineering :: Chemistry
Classifier: Topic :: Text Processing :: Filters
Classifier: Topic :: Utilities
Classifier: License :: OSI Approved :: MIT License
Classifier: Natural Language :: English
Classifier: Operating System :: Microsoft :: Windows :: Windows 7
Classifier: Operating System :: POSIX :: Linux
Classifier: Programming Language :: Python :: 3 :: Only
Classifier: Programming Language :: Python :: 3.4
Classifier: Programming Language :: Python :: 3.5
Classifier: Programming Language :: Python :: 3.6
Classifier: Programming Language :: Python :: Implementation :: CPython
